wp_client_aio/__init__.py
wp_client_aio/wordpress_client.py
wp_client_aio-1.0.5.dist-info/METADATA
wp_client_aio-1.0.5.dist-info/WHEEL
wp_client_aio-1.0.5.dist-info/RECORD
