Metadata-Version: 2.1
Name: wp-client-aio
Version: 1.0.5
Summary: Add a short description here
Author-email: Maxim Yurevich <maxim.yurewitch@gmail.com>
Requires-Python: >=3.11
Requires-Dist: aiohttp~=3.8.4
